coinbasepro/__init__.py
coinbasepro/auth.py
coinbasepro/auth_client.py
coinbasepro/exceptions.py
coinbasepro/public_client.py
coinbasepro/rate_limiter.py
coinbasepro/token_bucket.py
coinbasepro-0.4.2.dist-info/AUTHORS.md
coinbasepro-0.4.2.dist-info/LICENSE
coinbasepro-0.4.2.dist-info/METADATA
coinbasepro-0.4.2.dist-info/WHEEL
coinbasepro-0.4.2.dist-info/top_level.txt
coinbasepro-0.4.2.dist-info/RECORD
