Metadata-Version: 2.1
Name: coinbasepro
Version: 0.4.2
Summary: [Deprecated] A Python interface for the Coinbase Pro/Coinbase Exchange API.
Home-page: https://github.com/acontry/coinbasepro
Author: Alex Contryman
Author-email: acontry@gmail.com
License: MIT
Platform: UNKNOWN
Classifier: Development Status :: 7 - Inactive
Classifier: Intended Audience :: Developers
Classifier: Natural Language :: English
Classifier: License :: OSI Approved :: MIT License
Classifier: Programming Language :: Python
Classifier: Programming Language :: Python :: 3
Classifier: Programming Language :: Python :: 3.5
Classifier: Programming Language :: Python :: 3.6
Classifier: Programming Language :: Python :: 3.7
Classifier: Programming Language :: Python :: 3.8
Classifier: Programming Language :: Python :: 3.9
Classifier: Programming Language :: Python :: 3.10
Requires-Python: >=3.4
License-File: LICENSE
License-File: AUTHORS.md
Requires-Dist: requests (>=2.20.0)
Provides-Extra: dev
Requires-Dist: pip-tools ; extra == 'dev'
Requires-Dist: pre-commit ; extra == 'dev'
Requires-Dist: pygments ; extra == 'dev'
